{
  "particles": {
    "number": {
      "value": 100
    },
    "color": {
      "value": "#00ffa3"
    },
    "shape": {
      "type": "circle",
      "image": {
        "src": "hzs-logo.png",
        "width": 100,
        "height": 100
      }
    },
    "opacity": {
      "value": 0.5
    },
    "size": {
      "value": 3,
      "anim": {
        "enable": false,
        "speed": 10
      }
    },
    "interactivity": {
      "events": {
        "onhover": {
          "enable": true,
          "mode": "repulse"
        },
        "onclick": {
          "enable": true,
          "mode": "push"
        },
        "resize": true
      },
      "modes": {
        "repulse": {
          "distance": 50,
          "duration": 0.4
        }
      }
    }
  }
}
